<?xml version="1.0" encoding="UTF-8"?>
<config defaultdatabase="base" usedrelease="0" idlerelease="10" logcycle="5">
	<druid>
		<id>base</id>
		<type>DURID</type>
		<dbtype>MSSQL</dbtype>
		<schema>cooperop</schema>
		<driverClassName>com.microsoft.sqlserver.jdbc.SQLServerDriver</driverClassName>
		<url>jdbc:sqlserver://chaoran.crtech.cn:9204;DatabaseName=IADSCP</url>
		<username>sa</username>
		<password>www.sql2012.com</password>
		<!-- filters = stat 为运行sql监控  -->
		<filters>stat</filters>
		<initialSize>2</initialSize>
		<minIdle>2</minIdle>
		<maxActive>300</maxActive>
		<maxWait>60000</maxWait>
		<timeBetweenEvictionRunsMillis>60000</timeBetweenEvictionRunsMillis>
		<minEvictableIdleTimeMillis>300000</minEvictableIdleTimeMillis>
		<validationQuery>select 1</validationQuery>
		<testWhileIdle>true</testWhileIdle>
		<testOnBorrow>false</testOnBorrow>
		<testOnReturn>false</testOnReturn>
		<poolPreparedStatements>false</poolPreparedStatements>
		<maxPoolPreparedStatementPerConnectionSize>200</maxPoolPreparedStatementPerConnectionSize>
	</druid>
	<druid>
		<id>ipc</id>
		<type>DURID</type>
		<dbtype>MSSQL</dbtype>
		<schema>hospital_autopa</schema>
		<driverClassName>com.microsoft.sqlserver.jdbc.SQLServerDriver</driverClassName>
		<url>jdbc:sqlserver://chaoran.crtech.cn:9204;DatabaseName=hospital_autopa</url>
		<username>sa</username>
		<password>www.sql2012.com</password>
		<filters>stat</filters>
		<initialSize>2</initialSize>
		<minIdle>2</minIdle>
		<maxActive>300</maxActive>
		<maxWait>60000</maxWait>
		<timeBetweenEvictionRunsMillis>60000</timeBetweenEvictionRunsMillis>
		<minEvictableIdleTimeMillis>300000</minEvictableIdleTimeMillis>
		<validationQuery>select 1</validationQuery>
		<testWhileIdle>true</testWhileIdle>
		<testOnBorrow>false</testOnBorrow>
		<testOnReturn>false</testOnReturn>
		<poolPreparedStatements>false</poolPreparedStatements>
		<maxPoolPreparedStatementPerConnectionSize>200</maxPoolPreparedStatementPerConnectionSize>
	</druid>
	<druid>
		<id>hospital_imic</id>
		<type>DURID</type>
		<dbtype>MSSQL</dbtype>
		<schema>hospital_imic</schema>
		<driverClassName>com.microsoft.sqlserver.jdbc.SQLServerDriver</driverClassName>
		<url>jdbc:sqlserver://chaoran.crtech.cn:9204;DatabaseName=hospital_imic</url>
		<username>sa</username>
		<password>www.sql2012.com</password>
		<filters>stat</filters>
		<initialSize>2</initialSize>
		<minIdle>2</minIdle>
		<maxActive>300</maxActive>
		<maxWait>60000</maxWait>
		<timeBetweenEvictionRunsMillis>60000</timeBetweenEvictionRunsMillis>
		<minEvictableIdleTimeMillis>300000</minEvictableIdleTimeMillis>
		<validationQuery>select 1</validationQuery>
		<testWhileIdle>true</testWhileIdle>
		<testOnBorrow>false</testOnBorrow>
		<testOnReturn>false</testOnReturn>
		<poolPreparedStatements>false</poolPreparedStatements>
		<maxPoolPreparedStatementPerConnectionSize>200</maxPoolPreparedStatementPerConnectionSize>
	</druid>
	<druid>
		<id>hospital_oc</id>
		<type>DURID</type>
		<dbtype>MSSQL</dbtype>
		<schema>hospital_oc</schema>
		<driverClassName>com.microsoft.sqlserver.jdbc.SQLServerDriver</driverClassName>
		<url>jdbc:sqlserver://chaoran.crtech.cn:9204;DatabaseName=hospital_oc</url>
		<username>sa</username>
		<password>www.sql2012.com</password>
		<filters>stat</filters>
		<initialSize>2</initialSize>
		<minIdle>2</minIdle>
		<maxActive>300</maxActive>
		<maxWait>60000</maxWait>
		<timeBetweenEvictionRunsMillis>60000</timeBetweenEvictionRunsMillis>
		<minEvictableIdleTimeMillis>300000</minEvictableIdleTimeMillis>
		<validationQuery>select 1</validationQuery>
		<testWhileIdle>true</testWhileIdle>
		<testOnBorrow>false</testOnBorrow>
		<testOnReturn>false</testOnReturn>
		<poolPreparedStatements>false</poolPreparedStatements>
		<maxPoolPreparedStatementPerConnectionSize>200</maxPoolPreparedStatementPerConnectionSize>
	</druid>
	<druid>
		<id>autopa_thirdparty</id>
		<type>DURID</type>
		<dbtype>MSSQL</dbtype>
		<schema>autopa_thirdparty</schema>
		<driverClassName>com.microsoft.sqlserver.jdbc.SQLServerDriver</driverClassName>
		<url>jdbc:sqlserver://chaoran.crtech.cn:9204;DatabaseName=autopa_thirdparty</url>
		<username>sa</username>
		<password>www.sql2012.com</password>
		<filters>stat</filters>
		<initialSize>2</initialSize>
		<minIdle>2</minIdle>
		<maxActive>300</maxActive>
		<maxWait>60000</maxWait>
		<timeBetweenEvictionRunsMillis>60000</timeBetweenEvictionRunsMillis>
		<minEvictableIdleTimeMillis>300000</minEvictableIdleTimeMillis>
		<validationQuery>select 1</validationQuery>
		<testWhileIdle>true</testWhileIdle>
		<testOnBorrow>false</testOnBorrow>
		<testOnReturn>false</testOnReturn>
		<poolPreparedStatements>false</poolPreparedStatements>
		<maxPoolPreparedStatementPerConnectionSize>200</maxPoolPreparedStatementPerConnectionSize>
	</druid>
	<druid>
		<id>guide</id>
		<type>DURID</type>
		<dbtype>MSSQL</dbtype>
		<schema>guide</schema>
		<driverClassName>com.microsoft.sqlserver.jdbc.SQLServerDriver</driverClassName>
		<url>jdbc:sqlserver://chaoran.crtech.cn:9204;DatabaseName=guide</url>
		<username>sa</username>
		<password>www.sql2012.com</password>
		<filters>stat</filters>
		<initialSize>2</initialSize>
		<minIdle>2</minIdle>
		<maxActive>300</maxActive>
		<maxWait>60000</maxWait>
		<timeBetweenEvictionRunsMillis>60000</timeBetweenEvictionRunsMillis>
		<minEvictableIdleTimeMillis>300000</minEvictableIdleTimeMillis>
		<validationQuery>select 1</validationQuery>
		<testWhileIdle>true</testWhileIdle>
		<testOnBorrow>false</testOnBorrow>
		<testOnReturn>false</testOnReturn>
		<poolPreparedStatements>false</poolPreparedStatements>
		<maxPoolPreparedStatementPerConnectionSize>200</maxPoolPreparedStatementPerConnectionSize>
	</druid>
	<druid>
		<id>hospital_common</id>
		<type>DURID</type>
		<dbtype>MSSQL</dbtype>
		<schema>hospital_common</schema>
		<driverClassName>com.microsoft.sqlserver.jdbc.SQLServerDriver</driverClassName>
		<url>jdbc:sqlserver://chaoran.crtech.cn:9204;DatabaseName=hospital_common</url>
		<username>sa</username>
		<password>www.sql2012.com</password>
		<filters>stat</filters>
		<initialSize>2</initialSize>
		<minIdle>2</minIdle>
		<maxActive>300</maxActive>
		<maxWait>60000</maxWait>
		<timeBetweenEvictionRunsMillis>60000</timeBetweenEvictionRunsMillis>
		<minEvictableIdleTimeMillis>300000</minEvictableIdleTimeMillis>
		<validationQuery>select 1</validationQuery>
		<testWhileIdle>true</testWhileIdle>
		<testOnBorrow>false</testOnBorrow>
		<testOnReturn>false</testOnReturn>
		<poolPreparedStatements>false</poolPreparedStatements>
		<maxPoolPreparedStatementPerConnectionSize>200</maxPoolPreparedStatementPerConnectionSize>
	</druid>
	<druid>
		<id>im</id>
		<type>DURID</type>
		<dbtype>MSSQL</dbtype>
		<schema>im</schema>
		<driverClassName>com.microsoft.sqlserver.jdbc.SQLServerDriver</driverClassName>
		<url>jdbc:sqlserver://chaoran.crtech.cn:9204;DatabaseName=choho_im</url>
		<username>sa</username>
		<password>www.sql2012.com</password>
		<filters>stat</filters>
		<initialSize>2</initialSize>
		<minIdle>2</minIdle>
		<maxActive>300</maxActive>
		<maxWait>60000</maxWait>
		<timeBetweenEvictionRunsMillis>60000</timeBetweenEvictionRunsMillis>
		<minEvictableIdleTimeMillis>300000</minEvictableIdleTimeMillis>
		<validationQuery>select 1</validationQuery>
		<testWhileIdle>true</testWhileIdle>
		<testOnBorrow>false</testOnBorrow>
		<testOnReturn>false</testOnReturn>
		<poolPreparedStatements>false</poolPreparedStatements>
		<maxPoolPreparedStatementPerConnectionSize>200</maxPoolPreparedStatementPerConnectionSize>
	</druid>
</config>
